[
    {
        "package": "Rquefts",
        "url": "https://github.com/cropmodels/Rquefts"
    },
    {
        "package": "Rwofost",
        "url": "https://github.com/cropmodels/Rwofost"
    },
    {
        "package": "meteor",
        "url": "https://github.com/cropmodels/meteor"
    },
    {
        "package": "phenorice",
        "url": "https://github.com/cropmodels/phenorice"
    },
    {
        "package": "Recocrop",
        "url": "https://github.com/cropmodels/Recocrop"
    }   
]
